ahk_client/__init__.py
ahk_client/client.py
ahk_client-0.0.1.dist-info/LICENSE
ahk_client-0.0.1.dist-info/METADATA
ahk_client-0.0.1.dist-info/WHEEL
ahk_client-0.0.1.dist-info/top_level.txt
ahk_client-0.0.1.dist-info/RECORD
